xrtr.cpython-37m-x86_64-linux-gnu.so
xrtr-0.2.1.dist-info/RECORD
xrtr-0.2.1.dist-info/AUTHORS.rst
xrtr-0.2.1.dist-info/WHEEL
xrtr-0.2.1.dist-info/top_level.txt
xrtr-0.2.1.dist-info/LICENSE
xrtr-0.2.1.dist-info/METADATA
