Metadata-Version: 2.1
Name: xrtr
Version: 0.2.1
Summary: A Radix Tree based router for HTTP and other routing needs with support for middlewares and endpoints with a Cython boost
Home-page: https://github.com/vltr/xrtr
Author: Richard Kuesters
Author-email: rkuesters@gmail.com
License: UNKNOWN
Keywords: router,radix,tree,cython,trie,middleware,endpoint
Platform: UNKNOWN
Classifier: Development Status :: 3 - Alpha
Classifier: Intended Audience :: Developers
Classifier: License :: OSI Approved :: MIT License
Classifier: Operating System :: Unix
Classifier: Operating System :: POSIX
Classifier: Operating System :: Microsoft :: Windows
Classifier: Programming Language :: Python
Classifier: Programming Language :: Python :: 3.5
Classifier: Programming Language :: Python :: 3.6
Classifier: Programming Language :: Python :: 3.7
Classifier: Programming Language :: Python :: Implementation :: CPython
Classifier: Topic :: Utilities
Requires-Python: >=3.5
Requires-Dist: setuptools (>=19.0)
